{
    "title": "Drone Wall",
    "position": "470 318 1260 688",
    "power": "1",
    "saved": 0,
    "modules": [
        {
            "location": "1 1",
            "process": "Chaos Synth",
            "id": "Chaos Synth 966",
            "parameters": {
                "p3": "0.9684",
                "p18": "0.0040 0.0033 0.0031 0.0031 0.0033 0.0033 0.0033 0.0033 0.0031 0.0029 0.0031 0.0036 0.0038 0.0031 0.0040 0.0040 0.0036 0.0036 0.0036 0.0033 0.0036 0.0038 0.0042 0.0040",
                "p17": "138.4743 159.8270 186.5178 197.1942 202.5323 143.8125 122.4598 111.7835 111.7835 101.1072 79.7545 79.7545 95.7690 122.4598 170.5033 213.2087 218.5468 223.8850 229.2232 218.5468 207.8705 197.1942 186.5178 170.5033",
                "p5": "24",
                "p16": "1",
                "p22": "0",
                "p8": "7",
                "p7": "0",
                "p15": "30.0000 5000.0000",
                "p13": "370.0044",
                "p14": "12.9683",
                "p2": "M 1 Master 0",
                "p4": "10"
            }
        },
        {
            "location": "2 1",
            "process": "Moog Ladder Low Pass",
            "id": "Moog Ladder Low Pass 538",
            "parameters": {
                "p3": "1.0000",
                "p5": "0.5000",
                "p4": "1000.0000",
                "p1": "M 1"
            }
        }
    ]
}